scientiflow_cli/__init__.py
scientiflow_cli/__main__.py
scientiflow_cli/cli/__init__.py
scientiflow_cli/cli/auth_utils.py
scientiflow_cli/cli/login.py
scientiflow_cli/cli/logout.py
scientiflow_cli/config.py
scientiflow_cli/main.py
scientiflow_cli/pipeline/__init__.py
scientiflow_cli/pipeline/container_manager.py
scientiflow_cli/pipeline/decode_and_execute.py
scientiflow_cli/pipeline/get_jobs.py
scientiflow_cli/services/__init__.py
scientiflow_cli/services/auth_service.py
scientiflow_cli/services/base_directory.py
scientiflow_cli/services/executor.py
scientiflow_cli/services/request_handler.py
scientiflow_cli/services/rich_printer.py
scientiflow_cli/services/status_updater.py
scientiflow_cli/utils/__init__.py
scientiflow_cli/utils/encryption.py
scientiflow_cli/utils/file_manager.py
scientiflow_cli/utils/logger.py
scientiflow_cli/utils/mock.py
scientiflow_cli/utils/singularity.py
scientiflow_cli-0.4.7.dist-info/LICENSE.md
scientiflow_cli-0.4.7.dist-info/METADATA
scientiflow_cli-0.4.7.dist-info/WHEEL
scientiflow_cli-0.4.7.dist-info/entry_points.txt
scientiflow_cli-0.4.7.dist-info/RECORD
