Metadata-Version: 2.1
Name: scientiflow-cli
Version: 0.4.7
Summary: CLI tool for scientiflow. This application runs on the client side, decodes pipelines, and executes them in the configured order!
License: Proprietary
Author: ScientiFlow
Author-email: scientiflow@gmail.com
Requires-Python: >=3.8,<4.0
Classifier: License :: Other/Proprietary License
Classifier: Programming Language :: Python :: 3
Classifier: Programming Language :: Python :: 3.8
Classifier: Programming Language :: Python :: 3.9
Classifier: Programming Language :: Python :: 3.10
Classifier: Programming Language :: Python :: 3.11
Classifier: Programming Language :: Python :: 3.12
Requires-Dist: art (>=6.5,<7.0)
Requires-Dist: cryptography (>=43.0.1,<44.0.0)
Requires-Dist: pwinput (>=1.0.3,<2.0.0)
Requires-Dist: requests (>=2.31.0,<3.0.0)
Requires-Dist: rich (>=14.0.0,<15.0.0)
